Metadata-Version: 2.1
Name: jddo-probability
Version: 0.1
Summary: Gaussian and Binomial distributions
Author: Jola Olatunji
